tilepy_the_open_project/__init__.py
tilepy_the_open_project/example.py
tilepy_the_open_project-0.0.1.dist-info/LICENSE
tilepy_the_open_project-0.0.1.dist-info/METADATA
tilepy_the_open_project-0.0.1.dist-info/WHEEL
tilepy_the_open_project-0.0.1.dist-info/top_level.txt
tilepy_the_open_project-0.0.1.dist-info/RECORD
