Metadata-Version: 2.1
Name: tilepy-the-open-project
Version: 0.0.1
Summary: A simple, extremely easy-to-use Python GUI library, so you never ever make a single console app.
Author-email: Dylan Rogers <theopenprojectcode@gmail.com>
Project-URL: Homepage, https://github.com/DylanRogers1/tilepy
Project-URL: Bug Tracker, https://github.com/DylanRogers1/tilepy/issues
Classifier: Programming Language :: Python :: 3
Classifier: License :: OSI Approved :: MIT License
Classifier: Operating System :: OS Independent
Requires-Python: >=3.0
License-File: LICENSE
